{
  "dataset": "data/final_eval_texts.csv",
  "rows": 512,
  "hybrid_lexicon_weight": 0.85,
  "methods": {
    "lexicon": {
      "metrics": {
        "accuracy": 0.498,
        "macro_precision": 0.5651,
        "macro_recall": 0.498,
        "macro_f1": 0.4968,
        "total": 512,
        "per_label": {
          "anger": {
            "precision": 0.5128,
            "recall": 0.3125,
            "f1": 0.3883,
            "support": 64
          },
          "anticipation": {
            "precision": 0.2857,
            "recall": 0.3125,
            "f1": 0.2985,
            "support": 64
          },
          "disgust": {
            "precision": 0.7541,
            "recall": 0.7188,
            "f1": 0.736,
            "support": 64
          },
          "fear": {
            "precision": 0.3714,
            "recall": 0.8125,
            "f1": 0.5098,
            "support": 64
          },
          "joy": {
            "precision": 0.6452,
            "recall": 0.625,
            "f1": 0.6349,
            "support": 64
          },
          "sadness": {
            "precision": 0.9545,
            "recall": 0.3281,
            "f1": 0.4884,
            "support": 64
          },
          "surprise": {
            "precision": 0.3973,
            "recall": 0.4531,
            "f1": 0.4234,
            "support": 64
          },
          "trust": {
            "precision": 0.6,
            "recall": 0.4219,
            "f1": 0.4954,
            "support": 64
          }
        },
        "confusion": {
          "anger": {
            "anger": 20,
            "anticipation": 10,
            "disgust": 7,
            "fear": 12,
            "joy": 2,
            "sadness": 0,
            "surprise": 6,
            "trust": 7
          },
          "anticipation": {
            "anger": 2,
            "anticipation": 20,
            "disgust": 0,
            "fear": 28,
            "joy": 2,
            "sadness": 1,
            "surprise": 9,
            "trust": 2
          },
          "disgust": {
            "anger": 0,
            "anticipation": 7,
            "disgust": 46,
            "fear": 5,
            "joy": 1,
            "sadness": 0,
            "surprise": 5,
            "trust": 0
          },
          "fear": {
            "anger": 3,
            "anticipation": 2,
            "disgust": 2,
            "fear": 52,
            "joy": 4,
            "sadness": 0,
            "surprise": 1,
            "trust": 0
          },
          "joy": {
            "anger": 3,
            "anticipation": 6,
            "disgust": 0,
            "fear": 4,
            "joy": 40,
            "sadness": 0,
            "surprise": 9,
            "trust": 2
          },
          "sadness": {
            "anger": 3,
            "anticipation": 6,
            "disgust": 1,
            "fear": 15,
            "joy": 8,
            "sadness": 21,
            "surprise": 8,
            "trust": 2
          },
          "surprise": {
            "anger": 6,
            "anticipation": 8,
            "disgust": 5,
            "fear": 10,
            "joy": 1,
            "sadness": 0,
            "surprise": 29,
            "trust": 5
          },
          "trust": {
            "anger": 2,
            "anticipation": 11,
            "disgust": 0,
            "fear": 14,
            "joy": 4,
            "sadness": 0,
            "surprise": 6,
            "trust": 27
          }
        }
      },
      "predicted_distribution": {
        "anger": 39,
        "anticipation": 70,
        "disgust": 61,
        "fear": 140,
        "joy": 62,
        "sadness": 22,
        "surprise": 73,
        "trust": 45
      },
      "domain_metrics": {
        "blog": {
          "accuracy": 0.4821,
          "macro_precision": 0.5345,
          "macro_recall": 0.4821,
          "macro_f1": 0.4742,
          "total": 168
        },
        "news": {
          "accuracy": 0.4881,
          "macro_precision": 0.5539,
          "macro_recall": 0.4881,
          "macro_f1": 0.4823,
          "total": 168
        },
        "social": {
          "accuracy": 0.5227,
          "macro_precision": 0.6076,
          "macro_recall": 0.5227,
          "macro_f1": 0.5304,
          "total": 176
        }
      }
    },
    "nb": {
      "metrics": {
        "accuracy": 0.4062,
        "macro_precision": 0.5374,
        "macro_recall": 0.4062,
        "macro_f1": 0.3998,
        "total": 512,
        "per_label": {
          "anger": {
            "precision": 0.4268,
            "recall": 0.5469,
            "f1": 0.4795,
            "support": 64
          },
          "anticipation": {
            "precision": 0.3019,
            "recall": 0.25,
            "f1": 0.2735,
            "support": 64
          },
          "disgust": {
            "precision": 0.5833,
            "recall": 0.7656,
            "f1": 0.6622,
            "support": 64
          },
          "fear": {
            "precision": 0.2205,
            "recall": 0.6719,
            "f1": 0.332,
            "support": 64
          },
          "joy": {
            "precision": 0.697,
            "recall": 0.3594,
            "f1": 0.4742,
            "support": 64
          },
          "sadness": {
            "precision": 0.9231,
            "recall": 0.1875,
            "f1": 0.3117,
            "support": 64
          },
          "surprise": {
            "precision": 0.6667,
            "recall": 0.2812,
            "f1": 0.3956,
            "support": 64
          },
          "trust": {
            "precision": 0.48,
            "recall": 0.1875,
            "f1": 0.2697,
            "support": 64
          }
        },
        "confusion": {
          "anger": {
            "anger": 35,
            "anticipation": 2,
            "disgust": 13,
            "fear": 12,
            "joy": 0,
            "sadness": 1,
            "surprise": 0,
            "trust": 1
          },
          "anticipation": {
            "anger": 7,
            "anticipation": 16,
            "disgust": 1,
            "fear": 32,
            "joy": 0,
            "sadness": 0,
            "surprise": 2,
            "trust": 6
          },
          "disgust": {
            "anger": 2,
            "anticipation": 2,
            "disgust": 49,
            "fear": 10,
            "joy": 0,
            "sadness": 0,
            "surprise": 1,
            "trust": 0
          },
          "fear": {
            "anger": 6,
            "anticipation": 6,
            "disgust": 4,
            "fear": 43,
            "joy": 3,
            "sadness": 0,
            "surprise": 1,
            "trust": 1
          },
          "joy": {
            "anger": 11,
            "anticipation": 6,
            "disgust": 1,
            "fear": 20,
            "joy": 23,
            "sadness": 0,
            "surprise": 2,
            "trust": 1
          },
          "sadness": {
            "anger": 6,
            "anticipation": 3,
            "disgust": 5,
            "fear": 30,
            "joy": 5,
            "sadness": 12,
            "surprise": 2,
            "trust": 1
          },
          "surprise": {
            "anger": 8,
            "anticipation": 14,
            "disgust": 7,
            "fear": 13,
            "joy": 1,
            "sadness": 0,
            "surprise": 18,
            "trust": 3
          },
          "trust": {
            "anger": 7,
            "anticipation": 4,
            "disgust": 4,
            "fear": 35,
            "joy": 1,
            "sadness": 0,
            "surprise": 1,
            "trust": 12
          }
        }
      },
      "predicted_distribution": {
        "anger": 82,
        "anticipation": 53,
        "disgust": 84,
        "fear": 195,
        "joy": 33,
        "sadness": 13,
        "surprise": 27,
        "trust": 25
      },
      "domain_metrics": {
        "blog": {
          "accuracy": 0.4524,
          "macro_precision": 0.5523,
          "macro_recall": 0.4524,
          "macro_f1": 0.4477,
          "total": 168
        },
        "news": {
          "accuracy": 0.375,
          "macro_precision": 0.4825,
          "macro_recall": 0.375,
          "macro_f1": 0.3408,
          "total": 168
        },
        "social": {
          "accuracy": 0.392,
          "macro_precision": 0.5139,
          "macro_recall": 0.3921,
          "macro_f1": 0.3843,
          "total": 176
        }
      }
    },
    "hybrid": {
      "metrics": {
        "accuracy": 0.4766,
        "macro_precision": 0.5846,
        "macro_recall": 0.4766,
        "macro_f1": 0.48,
        "total": 512,
        "per_label": {
          "anger": {
            "precision": 0.5556,
            "recall": 0.5469,
            "f1": 0.5512,
            "support": 64
          },
          "anticipation": {
            "precision": 0.2982,
            "recall": 0.2656,
            "f1": 0.281,
            "support": 64
          },
          "disgust": {
            "precision": 0.6857,
            "recall": 0.75,
            "f1": 0.7164,
            "support": 64
          },
          "fear": {
            "precision": 0.2703,
            "recall": 0.7812,
            "f1": 0.4016,
            "support": 64
          },
          "joy": {
            "precision": 0.7174,
            "recall": 0.5156,
            "f1": 0.6,
            "support": 64
          },
          "sadness": {
            "precision": 0.9444,
            "recall": 0.2656,
            "f1": 0.4146,
            "support": 64
          },
          "surprise": {
            "precision": 0.6216,
            "recall": 0.3594,
            "f1": 0.4554,
            "support": 64
          },
          "trust": {
            "precision": 0.5833,
            "recall": 0.3281,
            "f1": 0.42,
            "support": 64
          }
        },
        "confusion": {
          "anger": {
            "anger": 35,
            "anticipation": 4,
            "disgust": 9,
            "fear": 14,
            "joy": 0,
            "sadness": 1,
            "surprise": 0,
            "trust": 1
          },
          "anticipation": {
            "anger": 4,
            "anticipation": 17,
            "disgust": 1,
            "fear": 33,
            "joy": 1,
            "sadness": 0,
            "surprise": 2,
            "trust": 6
          },
          "disgust": {
            "anger": 1,
            "anticipation": 3,
            "disgust": 48,
            "fear": 10,
            "joy": 0,
            "sadness": 0,
            "surprise": 2,
            "trust": 0
          },
          "fear": {
            "anger": 3,
            "anticipation": 3,
            "disgust": 5,
            "fear": 50,
            "joy": 2,
            "sadness": 0,
            "surprise": 1,
            "trust": 0
          },
          "joy": {
            "anger": 5,
            "anticipation": 7,
            "disgust": 0,
            "fear": 13,
            "joy": 33,
            "sadness": 0,
            "surprise": 4,
            "trust": 2
          },
          "sadness": {
            "anger": 5,
            "anticipation": 5,
            "disgust": 3,
            "fear": 24,
            "joy": 7,
            "sadness": 17,
            "surprise": 2,
            "trust": 1
          },
          "surprise": {
            "anger": 7,
            "anticipation": 12,
            "disgust": 4,
            "fear": 12,
            "joy": 1,
            "sadness": 0,
            "surprise": 23,
            "trust": 5
          },
          "trust": {
            "anger": 3,
            "anticipation": 6,
            "disgust": 0,
            "fear": 29,
            "joy": 2,
            "sadness": 0,
            "surprise": 3,
            "trust": 21
          }
        }
      },
      "predicted_distribution": {
        "anger": 63,
        "anticipation": 57,
        "disgust": 70,
        "fear": 185,
        "joy": 46,
        "sadness": 18,
        "surprise": 37,
        "trust": 36
      },
      "domain_metrics": {
        "blog": {
          "accuracy": 0.506,
          "macro_precision": 0.5684,
          "macro_recall": 0.506,
          "macro_f1": 0.4912,
          "total": 168
        },
        "news": {
          "accuracy": 0.4762,
          "macro_precision": 0.584,
          "macro_recall": 0.4762,
          "macro_f1": 0.475,
          "total": 168
        },
        "social": {
          "accuracy": 0.4489,
          "macro_precision": 0.567,
          "macro_recall": 0.4489,
          "macro_f1": 0.4524,
          "total": 176
        }
      }
    }
  },
  "gold_distribution": {
    "anger": 64,
    "anticipation": 64,
    "disgust": 64,
    "fear": 64,
    "joy": 64,
    "sadness": 64,
    "surprise": 64,
    "trust": 64
  }
}